encarno/__init__.py
encarno/bzt-configs.json
encarno/encarno-module.yml
encarno-0.5.3.dist-info/METADATA
encarno-0.5.3.dist-info/WHEEL
encarno-0.5.3.dist-info/top_level.txt
encarno-0.5.3.dist-info/RECORD
