Metadata-Version: 2.1
Name: encarno
Version: 0.5.3
Summary: Python module for Taurus to use Encarno load generator
Home-page: https://github.com/undera/encarno
Author: Andrei Pokhilko
Author-email: andrei.pokhilko@gmail.com
License: MIT
Requires-Dist: bzt
Requires-Dist: pyyaml
